zorge/__init__.py
zorge/definition/__init__.py
zorge/definition/contracts.py
zorge/definition/exceptions.py
zorge/implementation/__init__.py
zorge/implementation/container.py
zorge/implementation/provider.py
zorge/implementation/resolver.py
zorge-1.2.5.dist-info/LICENSE
zorge-1.2.5.dist-info/METADATA
zorge-1.2.5.dist-info/WHEEL
zorge-1.2.5.dist-info/RECORD
