Metadata-Version: 2.1
Name: zorge
Version: 1.2.5
Summary: Yet another implementation of dependency injection
Home-page: https://github.com/smairon/zorge
Author: Smairon
Author-email: man@smairon.ru
Requires-Python: >=3.11,<4.0
Classifier: Programming Language :: Python :: 3
Classifier: Programming Language :: Python :: 3.11
Classifier: Programming Language :: Python :: 3.12
Project-URL: Repository, https://github.com/smairon/zorge
